CentralizedAppraiser/__init__.py
CentralizedAppraiser/utils.py
CentralizedAppraiser/UnitedStates/__init__.py
CentralizedAppraiser/UnitedStates/geometry.geojson
CentralizedAppraiser/UnitedStates/Florida/__init__.py
CentralizedAppraiser/UnitedStates/Florida/geometry.geojson
CentralizedAppraiser/UnitedStates/Florida/Broward/__init__.py
CentralizedAppraiser/UnitedStates/Florida/Broward/_examples/494229030620.json
CentralizedAppraiser/UnitedStates/Florida/Broward/_examples/504109270060.json
CentralizedAppraiser/UnitedStates/Florida/Broward/_examples/504115280010.json
CentralizedAppraiser/UnitedStates/Florida/MiamiDade/__init__.py
CentralizedAppraiser/UnitedStates/Florida/MiamiDade/_examples/1079160030960.json
CentralizedAppraiser/UnitedStates/Florida/MiamiDade/_examples/1678240260150.json
CentralizedAppraiser/UnitedStates/Florida/MiamiDade/_examples/3078150000422.json
CentralizedAppraiser/abstracts/__init__.py
CentralizedAppraiser/abstracts/_address.py
CentralizedAppraiser/abstracts/_client.py
CentralizedAppraiser/abstracts/_location.py
CentralizedAppraiser-0.0.9.dist-info/LICENSE
CentralizedAppraiser-0.0.9.dist-info/METADATA
CentralizedAppraiser-0.0.9.dist-info/WHEEL
CentralizedAppraiser-0.0.9.dist-info/top_level.txt
CentralizedAppraiser-0.0.9.dist-info/RECORD
