Metadata-Version: 2.1
Name: CentralizedAppraiser
Version: 0.0.9
Summary: A centralized method of accessing appraiser data, using each counties local property appraiser's data.
Author-email: "Reed Graff (Compliancy)" <reed@withcompliancy.com>
License: MIT License
Project-URL: Homepage, https://github.com/ReedGraff/CentralizedAppraiser
Project-URL: Issues, https://github.com/ReedGraff/CentralizedAppraiser/issues
Keywords: real estate,appraiser,property,data,centralized,api
Classifier: Programming Language :: Python :: 3
Classifier: License :: OSI Approved :: MIT License
Classifier: Operating System :: OS Independent
Requires-Python: >=3.8
License-File: LICENSE
Requires-Dist: requests
Requires-Dist: shapely
Requires-Dist: schema
Requires-Dist: pyproj
